stalcraft/__init__.py
stalcraft/consts.py
stalcraft/defaults.py
stalcraft/enums.py
stalcraft/exceptions.py
stalcraft/api/__init__.py
stalcraft/api/base.py
stalcraft/api/secret.py
stalcraft/api/token.py
stalcraft/asyncio/__init__.py
stalcraft/asyncio/api/__init__.py
stalcraft/asyncio/api/base.py
stalcraft/asyncio/api/secret.py
stalcraft/asyncio/api/token.py
stalcraft/asyncio/auction/__init__.py
stalcraft/asyncio/auction/auction.py
stalcraft/asyncio/auth/__init__.py
stalcraft/asyncio/auth/app.py
stalcraft/asyncio/auth/base.py
stalcraft/asyncio/auth/user.py
stalcraft/asyncio/clan/__init__.py
stalcraft/asyncio/clan/clan.py
stalcraft/asyncio/clan/user.py
stalcraft/asyncio/client/__init__.py
stalcraft/asyncio/client/app.py
stalcraft/asyncio/client/base.py
stalcraft/asyncio/client/user.py
stalcraft/auction/__init__.py
stalcraft/auction/auction.py
stalcraft/auth/__init__.py
stalcraft/auth/app.py
stalcraft/auth/base.py
stalcraft/auth/user.py
stalcraft/clan/__init__.py
stalcraft/clan/clan.py
stalcraft/clan/user.py
stalcraft/client/__init__.py
stalcraft/client/app.py
stalcraft/client/base.py
stalcraft/client/user.py
stalcraft/items/__init__.py
stalcraft/items/base.py
stalcraft/items/local.py
stalcraft/items/web.py
stalcraft/items/listing/global/listing.json
stalcraft/items/listing/ru/listing.json
stalcraft/schemas/__init__.py
stalcraft/schemas/api.py
stalcraft/schemas/auth.py
stalcraft/schemas/ratelimit.py
stalcraft/utils/__init__.py
stalcraft/utils/listing.py
stalcraft_api-1.2.0.dist-info/licenses/LICENSE
stalcraft_api-1.2.0.dist-info/METADATA
stalcraft_api-1.2.0.dist-info/WHEEL
stalcraft_api-1.2.0.dist-info/top_level.txt
stalcraft_api-1.2.0.dist-info/RECORD
