Metadata-Version: 2.4
Name: stalcraft-api
Version: 1.2.0
Summary: stalcraft api unofficial python library
Author-email: onejeuu <mail@66rk.ru>
License-Expression: MIT
Project-URL: Repository, https://github.com/onejeuu/stalcraft-api
Keywords: stalcraft,api,stalcraft-api,api-client
Requires-Python: >=3.11
License-File: LICENSE
Requires-Dist: pydantic>=1.10.0
Requires-Dist: httpx>=0.25.0
Dynamic: license-file
